{
   "html_attributions" : [],
   "results" : [
      {
         "geometry" : {
            "location" : {
               "lat" : -33.8585416,
               "lng" : 151.2100441
            },
            "viewport" : {
               "northeast" : {
                  "lat" : -33.85717357010728,
                  "lng" : 151.2112493798927
               },
               "southwest" : {
                  "lat" : -33.85987322989273,
                  "lng" : 151.2085497201073
               }
            }
         },
         "icon" : "https://maps.gstatic.com/mapfiles/place_api/icons/bar-71.png",
         "id" : "8e980ad0c819c33cdb1cea31e72d654ca61a7065",
         "name" : "Cruise Bar",
         "opening_hours" : {
            "open_now" : true
         },
         "photos" : [
            {
               "height" : 608,
               "html_attributions" : [
                  "\u003ca href=\"https://maps.google.com/maps/contrib/112582655193348962755\"\u003eA Google User\u003c/a\u003e"
               ],
               "photo_reference" : "CmRaAAAAbe7gUsk1GGAN8sz_kBspJ7lM7_FYnnQAZ3UKLK_GrmI3YNCuyomjY__FJIoWsbngF8pGj0Pm3TPLtvw_UIS4p1mGtKExwVSEtO8lqhM9elzZcYIkPnxGibGL591uCBbJEhA-HF8n53kSktFWV4vXSMthGhTNwVCNefdl9RZiYdv1KaBVrjh24A",
               "width" : 1080
            }
         ],
         "place_id" : "ChIJi6C1MxquEmsR9-c-3O48ykI",
         "plus_code" : {
            "compound_code" : "46R6+H2 The Rocks, New South Wales",
            "global_code" : "4RRH46R6+H2"
         },
         "price_level" : 2,
         "rating" : 4,
         "reference" : "ChIJi6C1MxquEmsR9-c-3O48ykI",
         "scope" : "GOOGLE",
         "types" : [ "bar", "restaurant", "food", "point_of_interest", "establishment" ],
         "user_ratings_total" : 942,
         "vicinity" : "Level 1, 2 and 3, Overseas Passenger Terminal, Circular Quay W, The Rocks"
      },
      {
         "geometry" : {
            "location" : {
               "lat" : -33.8677371,
               "lng" : 151.2016936
            },
            "viewport" : {
               "northeast" : {
                  "lat" : -33.86637842010727,
                  "lng" : 151.2031597798928
               },
               "southwest" : {
                  "lat" : -33.86907807989272,
                  "lng" : 151.2004601201073
               }
            }
         },
         "icon" : "https://maps.gstatic.com/mapfiles/place_api/icons/generic_business-71.png",
         "id" : "f1e044040bd03ff06e19de4798b52dd926855281",
         "name" : "Sydney Harbour Dinner Cruises",
         "opening_hours" : {
            "open_now" : false
         },
         "photos" : [
            {
               "height" : 835,
               "html_attributions" : [
                  "\u003ca href=\"https://maps.google.com/maps/contrib/109764923610545394994\"\u003eA Google User\u003c/a\u003e"
               ],
               "photo_reference" : "CmRaAAAAcnAHJSwewG1F7m_GPhABgCmo9igEGTTWTvPBMeQzJmcF8arPhdphGQxl0-cOC_tfKPuvNdSA9s_ysaIvNQcwjfMb5xsCMdrj3I81cpdT48WT8opQPxt8OfFBL3QkP1DcEhCpdrh177zPF_89B8qSUvdJGhSI4lvhx0NaPT2lDE7IjFhdAdE__A",
               "width" : 1200
            }
         ],
         "place_id" : "ChIJM1mOVTS6EmsRKaDzrTsgids",
         "plus_code" : {
            "compound_code" : "46J2+WM Sydney, New South Wales",
            "global_code" : "4RRH46J2+WM"
         },
         "rating" : 5,
         "reference" : "ChIJM1mOVTS6EmsRKaDzrTsgids",
         "scope" : "GOOGLE",
         "types" : [
            "tourist_attraction",
            "travel_agency",
            "restaurant",
            "food",
            "point_of_interest",
            "establishment"
         ],
         "user_ratings_total" : 2,
         "vicinity" : "32 The Promenade, Sydney"
      },
      {
         "geometry" : {
            "location" : {
               "lat" : -33.8609391,
               "lng" : 151.2098735
            },
            "viewport" : {
               "northeast" : {
                  "lat" : -33.85958927010727,
                  "lng" : 151.2112233298927
               },
               "southwest" : {
                  "lat" : -33.86228892989272,
                  "lng" : 151.2085236701072
               }
            }
         },
         "icon" : "https://maps.gstatic.com/mapfiles/place_api/icons/generic_business-71.png",
         "id" : "9ea7c77cb181b1f33d19c9d76121fcc6d5246ad8",
         "name" : "Australian Cruise Group",
         "opening_hours" : {
            "open_now" : false
         },
         "photos" : [
            {
               "height" : 1536,
               "html_attributions" : [
                  "\u003ca href=\"https://maps.google.com/maps/contrib/113088009011192061895\"\u003eKeith Bauman\u003c/a\u003e"
               ],
               "photo_reference" : "CmRaAAAABQIx3YKjqIdGOhXK3axi8PRLUhCJmwUBa_vPt1fdnWY5TiWo4773MVTuuV1P3m2XR7wiLX15ZbLKdEi8HnabIFkaGgzith8Bks6YXl83I_7O8e1G71RtsoHQOmLCQTBJEhAZ-J77S9FS_th08LRqHIwrGhQHh9u3MZauJUWhnZvsATm5ArDDuA",
               "width" : 2048
            }
         ],
         "place_id" : "ChIJpU8KgUKuEmsRKErVGEaa11w",
         "plus_code" : {
            "compound_code" : "46Q5+JW Sydney, New South Wales",
            "global_code" : "4RRH46Q5+JW"
         },
         "rating" : 4.4,
         "reference" : "ChIJpU8KgUKuEmsRKErVGEaa11w",
         "scope" : "GOOGLE",
         "types" : [
            "travel_agency",
            "restaurant",
            "food",
            "point_of_interest",
            "establishment"
         ],
         "user_ratings_total" : 5,
         "vicinity" : "6 Cirular Quay, Sydney"
      },
      {
         "geometry" : {
            "location" : {
               "lat" : -33.8686058,
               "lng" : 151.2018206
            },
            "viewport" : {
               "northeast" : {
                  "lat" : -33.86724947010728,
                  "lng" : 151.2032704798927
               },
               "southwest" : {
                  "lat" : -33.86994912989272,
                  "lng" : 151.2005708201072
               }
            }
         },
         "icon" : "https://maps.gstatic.com/mapfiles/place_api/icons/generic_business-71.png",
         "id" : "21a0b251c9b8392186142c798263e289fe45b4aa",
         "name" : "Rhythmboat Cruises",
         "opening_hours" : {
            "open_now" : false
         },
         "photos" : [
            {
               "height" : 2269,
               "html_attributions" : [
                  "\u003ca href=\"https://maps.google.com/maps/contrib/104066891898402903288\"\u003eRhythmboat Sydney Harbour Cruises\u003c/a\u003e"
               ],
               "photo_reference" : "CmRaAAAAZNfKw23dFd57zSBHaBNQV3I2horE7YDoXY7JLjOIUJSZMHW_57Z-BUg1PCYhxRoRnT9Hrp7AJAjse4MkI6MkQGDZqooZY8ShUOLxq-YsoQe0VQ3ZkH2KxqPc_vyiYyATEhBm0791L876Z1BV5-Wlk2ZSGhTi22tib3N3RPnFKE5ch0ebOXYsbA",
               "width" : 4032
            }
         ],
         "place_id" : "ChIJyWEHuEmuEmsRm9hTkapTCrk",
         "plus_code" : {
            "compound_code" : "46J2+HP Sydney, New South Wales",
            "global_code" : "4RRH46J2+HP"
         },
         "rating" : 4,
         "reference" : "ChIJyWEHuEmuEmsRm9hTkapTCrk",
         "scope" : "GOOGLE",
         "types" : [
            "travel_agency",
            "restaurant",
            "food",
            "point_of_interest",
            "establishment"
         ],
         "user_ratings_total" : 27,
         "vicinity" : "King Street Wharf, King St, Sydney"
      },
      {
         "geometry" : {
            "location" : {
               "lat" : -33.8584902,
               "lng" : 151.2099067
            },
            "viewport" : {
               "northeast" : {
                  "lat" : -33.85713117010727,
                  "lng" : 151.2111837298927
               },
               "southwest" : {
                  "lat" : -33.85983082989272,
                  "lng" : 151.2084840701073
               }
            }
         },
         "icon" : "https://maps.gstatic.com/mapfiles/place_api/icons/restaurant-71.png",
         "id" : "6facf611e56f3d6f232a24e60d9392759bbd43fa",
         "name" : "Junk Lounge",
         "opening_hours" : {
            "open_now" : false
         },
         "photos" : [
            {
               "height" : 608,
               "html_attributions" : [
                  "\u003ca href=\"https://maps.google.com/maps/contrib/104473997089847488714\"\u003eA Google User\u003c/a\u003e"
               ],
               "photo_reference" : "CmRaAAAAbC8DoWZzr5gnqW1x4a5q97hwJNgMUiFQNgmuzR510FJ0YKG0GYvvSnMlrR8B0KVvgmwvQ9LLdzlWwC8zQQwN5jUjumigIXLVOO00mNJ5QZs7UlhkhQH0CJrDzRm6yb9XEhDeE8tpLNidlAGJDr_Dp_-DGhTRJboI23uXFfmOmDk5eag4Euogjg",
               "width" : 1080
            }
         ],
         "place_id" : "ChIJq9W3HZOvEmsRYtKNTRmq34M",
         "plus_code" : {
            "compound_code" : "46R5+JX The Rocks, New South Wales",
            "global_code" : "4RRH46R5+JX"
         },
         "price_level" : 2,
         "rating" : 4.1,
         "reference" : "ChIJq9W3HZOvEmsRYtKNTRmq34M",
         "scope" : "GOOGLE",
         "types" : [ "restaurant", "food", "point_of_interest", "establishment" ],
         "user_ratings_total" : 29,
         "vicinity" : "Level 2, Overseas Passenger Terminal, Circular Quay W, The Rocks"
      },
      {
         "geometry" : {
            "location" : {
               "lat" : -33.8675865,
               "lng" : 151.2015918
            },
            "viewport" : {
               "northeast" : {
                  "lat" : -33.86618707010727,
                  "lng" : 151.2029995798927
               },
               "southwest" : {
                  "lat" : -33.86888672989271,
                  "lng" : 151.2002999201073
               }
            }
         },
         "icon" : "https://maps.gstatic.com/mapfiles/place_api/icons/generic_business-71.png",
         "id" : "0f0b34443f580704d5bc9975b02066cf6ab3d79e",
         "name" : "Sydney Harbour Lunch Cruise",
         "opening_hours" : {
            "open_now" : false
         },
         "photos" : [
            {
               "height" : 545,
               "html_attributions" : [
                  "\u003ca href=\"https://maps.google.com/maps/contrib/102428257696490257922\"\u003eSydney Harbour Lunch Cruise\u003c/a\u003e"
               ],
               "photo_reference" : "CmRaAAAAAw8pxeXWproc0WWfydcy1eTgxkiBJS1KpQ619lzgsGOj1uYeX6ck25SKow4JP7_Rt8oDfHtn_m7jEbJ3t2_K53F2q6Bd18PipqAk6HkKcTOpmVBEulYe3y8OlQT5gUqpEhADNz-T0x79o6jY_3LsEzNVGhTJeacZ24IN042OtCtiVWINYGucYg",
               "width" : 969
            }
         ],
         "place_id" : "ChIJUbf3iDiuEmsROJxXbhYO7cM",
         "plus_code" : {
            "compound_code" : "46J2+XJ Sydney, New South Wales",
            "global_code" : "4RRH46J2+XJ"
         },
         "rating" : 3.8,
         "reference" : "ChIJUbf3iDiuEmsROJxXbhYO7cM",
         "scope" : "GOOGLE",
         "types" : [
            "travel_agency",
            "restaurant",
            "food",
            "point_of_interest",
            "establishment"
         ],
         "user_ratings_total" : 16,
         "vicinity" : "5/32 The Promenade, Sydney"
      },
      {
         "geometry" : {
            "location" : {
               "lat" : -33.8675885,
               "lng" : 151.2015896
            },
            "viewport" : {
               "northeast" : {
                  "lat" : -33.86618797010728,
                  "lng" : 151.2029996798927
               },
               "southwest" : {
                  "lat" : -33.86888762989273,
                  "lng" : 151.2003000201072
               }
            }
         },
         "icon" : "https://maps.gstatic.com/mapfiles/place_api/icons/generic_business-71.png",
         "id" : "dec25eec746943ffbc96e3719623dbbb12d4d2a2",
         "name" : "Magistic Cruises",
         "opening_hours" : {
            "open_now" : false
         },
         "photos" : [
            {
               "height" : 384,
               "html_attributions" : [
                  "\u003ca href=\"https://maps.google.com/maps/contrib/108269116761340400861\"\u003eMagistic Cruises\u003c/a\u003e"
               ],
               "photo_reference" : "CmRaAAAAEgJFwX1F6Au3WsEPVHcl4k3XgxC5bWfDkCWXVpwGZjU-EB_1RuXM76JOzLKNGRv8tSyLk3RyfRs3esLOJbce_wKGvD9L9SYAAjXjeaP7T74t_vOKIzUAku9ERlyRW_WEEhCSyt400oslQq4CE_3gNAOVGhQAiidafAiJh2JkG84ZDu_M8QxNrw",
               "width" : 512
            }
         ],
         "place_id" : "ChIJxRjqYTiuEmsRGebAA_chDLE",
         "plus_code" : {
            "compound_code" : "46J2+XJ Sydney, New South Wales",
            "global_code" : "4RRH46J2+XJ"
         },
         "rating" : 3.9,
         "reference" : "ChIJxRjqYTiuEmsRGebAA_chDLE",
         "scope" : "GOOGLE",
         "types" : [
            "tourist_attraction",
            "travel_agency",
            "restaurant",
            "food",
            "point_of_interest",
            "establishment"
         ],
         "user_ratings_total" : 76,
         "vicinity" : "King Street Wharf, 32 The Promenade, Sydney"
      },
      {
         "geometry" : {
            "location" : {
               "lat" : -33.8582724,
               "lng" : 151.2100117
            },
            "viewport" : {
               "northeast" : {
                  "lat" : -33.85690727010728,
                  "lng" : 151.2112615298927
               },
               "southwest" : {
                  "lat" : -33.85960692989272,
                  "lng" : 151.2085618701073
               }
            }
         },
         "icon" : "https://maps.gstatic.com/mapfiles/place_api/icons/restaurant-71.png",
         "id" : "968577d1adec336585598220ccaba8e05f3b9b54",
         "name" : "Yuki's at the Quay",
         "opening_hours" : {
            "open_now" : false
         },
         "photos" : [
            {
               "height" : 1313,
               "html_attributions" : [
                  "\u003ca href=\"https://maps.google.com/maps/contrib/111950905810286881605\"\u003eA Google User\u003c/a\u003e"
               ],
               "photo_reference" : "CmRaAAAAVh4jnvRjUL_RjMsn3SZuvmeIdwkdW78NF9VGDsaVw_US-VKCuZiQEocDTdokoMoLEAZKJxA3SS2TtDTyZGAL_djSD-OFV02wlpnbscWHkl9Aq_S9kzoIJk4d0Q6x2d1-EhBPQ-zQivbtX1w2gtZkM-_UGhRO3ujsTcEunVsbWp_GfM9pJjfZjA",
               "width" : 1980
            }
         ],
         "place_id" : "ChIJkUcHV12uEmsRdEyuYJC4zDk",
         "plus_code" : {
            "compound_code" : "46R6+M2 The Rocks, New South Wales",
            "global_code" : "4RRH46R6+M2"
         },
         "price_level" : 2,
         "rating" : 4,
         "reference" : "ChIJkUcHV12uEmsRdEyuYJC4zDk",
         "scope" : "GOOGLE",
         "types" : [ "restaurant", "food", "point_of_interest", "establishment" ],
         "user_ratings_total" : 101,
         "vicinity" : "Level 4 Overseas Passenger Terminal, The Rocks"
      },
      {
         "geometry" : {
            "location" : {
               "lat" : -33.8778101,
               "lng" : 151.2036458
            },
            "viewport" : {
               "northeast" : {
                  "lat" : -33.87651932010728,
                  "lng" : 151.2049828298927
               },
               "southwest" : {
                  "lat" : -33.87921897989273,
                  "lng" : 151.2022831701073
               }
            }
         },
         "icon" : "https://maps.gstatic.com/mapfiles/place_api/icons/restaurant-71.png",
         "id" : "b0b8a475f3ed85e4122065af31465ccdaa71df98",
         "name" : "At Thai Cuisine (ร้านกินปลา)",
         "opening_hours" : {
            "open_now" : false
         },
         "photos" : [
            {
               "height" : 1837,
               "html_attributions" : [
                  "\u003ca href=\"https://maps.google.com/maps/contrib/104337509705732808533\"\u003eA Google User\u003c/a\u003e"
               ],
               "photo_reference" : "CmRZAAAAkXG7fwEHK6aiWzX07GfhdWKx6_hdcYP9F36oBhBxJvj_2UHOvM4DSq4SPhFUo8Ia2jVO_TBAqWt4PB8CNLAT8c9MVkIGhAFe55RmQ3-MRCb5dVSIQI46GBoyaBJlQvLvEhCjxyWQnzWmvsGf-BqIpx5wGhTEJiSiDlYD_4IdKo3zXwzQXtiE5A",
               "width" : 3264
            }
         ],
         "place_id" : "ChIJv2VysiSuEmsR_d5YoJkGpaQ",
         "plus_code" : {
            "compound_code" : "46C3+VF Haymarket, New South Wales",
            "global_code" : "4RRH46C3+VF"
         },
         "rating" : 4.4,
         "reference" : "ChIJv2VysiSuEmsR_d5YoJkGpaQ",
         "scope" : "GOOGLE",
         "types" : [ "restaurant", "food", "point_of_interest", "establishment" ],
         "user_ratings_total" : 45,
         "vicinity" : "Shop 209/25 - 29 Dixon St, Haymarket"
      },
      {
         "geometry" : {
            "location" : {
               "lat" : -33.873825,
               "lng" : 151.192584
            },
            "viewport" : {
               "northeast" : {
                  "lat" : -33.87247632010728,
                  "lng" : 151.1939354798927
               },
               "southwest" : {
                  "lat" : -33.87517597989272,
                  "lng" : 151.1912358201073
               }
            }
         },
         "icon" : "https://maps.gstatic.com/mapfiles/place_api/icons/generic_business-71.png",
         "id" : "48d507d8c878b31eca0b7067698195ab57904c75",
         "name" : "Twin Peeks Afloat - Sydney's only luxury adult entertainment cruise",
         "opening_hours" : {
            "open_now" : false
         },
         "photos" : [
            {
               "height" : 500,
               "html_attributions" : [
                  "\u003ca href=\"https://maps.google.com/maps/contrib/112593646930206915862\"\u003eTwin Peeks Afloat - Sydney&#39;s only luxury adult entertainment cruise\u003c/a\u003e"
               ],
               "photo_reference" : "CmRaAAAAGTp9JGYUNu6-9HcBk_m7b0AqBOkk2fcfXJOgbuQcvPuhEvIBNQqOLbmY12ZqRO11F8RmSyXyRvOZqedxS_CY_3CdFslVl_MLM5SDHvuRzYHSz5MuHSLT4bSiuQ0aFnl3EhD_n4XvVza3h77CjnZN7WffGhTGJhh5xnziKKzFfu776Qtttljnlw",
               "width" : 333
            }
         ],
         "place_id" : "ChIJD5bUHTKuEmsRhoLAfaJq86U",
         "plus_code" : {
            "compound_code" : "45GV+F2 Pyrmont, New South Wales",
            "global_code" : "4RRH45GV+F2"
         },
         "rating" : 0,
         "reference" : "ChIJD5bUHTKuEmsRhoLAfaJq86U",
         "scope" : "GOOGLE",
         "types" : [
            "travel_agency",
            "restaurant",
            "food",
            "point_of_interest",
            "establishment"
         ],
         "user_ratings_total" : 0,
         "vicinity" : "155/3 Pyrmont Bridge Rd, Pyrmont"
      },
      {
         "geometry" : {
            "location" : {
               "lat" : -33.8567519,
               "lng" : 151.2049127
            },
            "viewport" : {
               "northeast" : {
                  "lat" : -33.85549117010728,
                  "lng" : 151.2062767298927
               },
               "southwest" : {
                  "lat" : -33.85819082989272,
                  "lng" : 151.2035770701073
               }
            }
         },
         "icon" : "https://maps.gstatic.com/mapfiles/place_api/icons/restaurant-71.png",
         "id" : "12ecbb364c858ef4f4e54d42d4fd9d6f1abb2c6d",
         "name" : "Lavana Restaurant",
         "opening_hours" : {
            "open_now" : false
         },
         "photos" : [
            {
               "height" : 809,
               "html_attributions" : [
                  "\u003ca href=\"https://maps.google.com/maps/contrib/118254595749042091496\"\u003eA Google User\u003c/a\u003e"
               ],
               "photo_reference" : "CmRaAAAAovZaAB7v9J3X-vHSFRVLnKyvbIEdPE6f3TQXUPvLNi627smkk7UBhPTD3pAX3P8IvEwng4i4JGuSK9wOaA0KPIysqnpijv_LgYw2lDFTPSGb6SxFRDshUnzNb2RPAKkhEhD45UHu3SSYsb51lTBYjrTdGhTR-1ISIj-6ip_voDt37g5hFSIXeQ",
               "width" : 1440
            }
         ],
         "place_id" : "ChIJH0fipVyuEmsRmLcS6SvODcE",
         "plus_code" : {
            "compound_code" : "46V3+7X Dawes Point, New South Wales",
            "global_code" : "4RRH46V3+7X"
         },
         "price_level" : 2,
         "rating" : 4.2,
         "reference" : "ChIJH0fipVyuEmsRmLcS6SvODcE",
         "scope" : "GOOGLE",
         "types" : [
            "restaurant",
            "cafe",
            "bar",
            "food",
            "point_of_interest",
            "store",
            "establishment"
         ],
         "user_ratings_total" : 183,
         "vicinity" : "6/17A Hickson Rd, Dawes Point"
      },
      {
         "geometry" : {
            "location" : {
               "lat" : -33.8806594,
               "lng" : 151.2046664
            },
            "viewport" : {
               "northeast" : {
                  "lat" : -33.87934012010728,
                  "lng" : 151.2061456298927
               },
               "southwest" : {
                  "lat" : -33.88203977989272,
                  "lng" : 151.2034459701072
               }
            }
         },
         "icon" : "https://maps.gstatic.com/mapfiles/place_api/icons/restaurant-71.png",
         "id" : "2eb6ebf9434f22258a772bf11b381a7bf26f6411",
         "name" : "Pho Pasteur",
         "opening_hours" : {
            "open_now" : false
         },
         "photos" : [
            {
               "height" : 2319,
               "html_attributions" : [
                  "\u003ca href=\"https://maps.google.com/maps/contrib/113610891890774395703\"\u003eBriggs Jourdan\u003c/a\u003e"
               ],
               "photo_reference" : "CmRaAAAAVUrUTVD2_VtM1JoPgj6KSjVPed80OYY1aOu0vik90GXj0v-xR5b2vq9SxxHl5JkBGFTd3jKYBPUBNyGNS3inqU0p31BSe_0F8c_zS1pIp71Lzbjt8QWRSZ329a8ZW6b9EhD_wKtPXtmSBj96YsxBnj3uGhS2flt06TXXOhv8TLplyJbYLqV74g",
               "width" : 3211
            }
         ],
         "place_id" : "ChIJ-WqPgyOuEmsRZGa1fiF-wGc",
         "plus_code" : {
            "compound_code" : "4693+PV Haymarket, New South Wales",
            "global_code" : "4RRH4693+PV"
         },
         "price_level" : 1,
         "rating" : 3.7,
         "reference" : "ChIJ-WqPgyOuEmsRZGa1fiF-wGc",
         "scope" : "GOOGLE",
         "types" : [ "restaurant", "food", "point_of_interest", "establishment" ],
         "user_ratings_total" : 397,
         "vicinity" : "709 George St, Haymarket"
      },
      {
         "geometry" : {
            "location" : {
               "lat" : -33.85859,
               "lng" : 151.2091896
            },
            "viewport" : {
               "northeast" : {
                  "lat" : -33.85722487010728,
                  "lng" : 151.2104743298927
               },
               "southwest" : {
                  "lat" : -33.85992452989272,
                  "lng" : 151.2077746701073
               }
            }
         },
         "icon" : "https://maps.gstatic.com/mapfiles/place_api/icons/restaurant-71.png",
         "id" : "28d79e58234567dccd75bc999834483a3e9ef914",
         "name" : "Wild Ginger Dining + Bar",
         "opening_hours" : {
            "open_now" : false
         },
         "photos" : [
            {
               "height" : 315,
               "html_attributions" : [
                  "\u003ca href=\"https://maps.google.com/maps/contrib/108137778397307449630\"\u003eWild Ginger Dining + Bar\u003c/a\u003e"
               ],
               "photo_reference" : "CmRaAAAA_T85n-kc43ZgUbki4MMaJEQYDJcLXGBON5pfxQXs7FMKnfs6SWD4ZQI4VTyeq8wV8-GIP8MYTiAP9FLuAzLdtxthAMYhSRuL8y3gnRECfelFsRlidNXTjNFOOimD6Z9NEhBzf4HinQN9NeGuGOLlBg1zGhSaVbBlqNhC1enPxCbX0LCsHFXlIg",
               "width" : 828
            }
         ],
         "place_id" : "ChIJbyKrs0KuEmsRx9fE2LPB08U",
         "plus_code" : {
            "compound_code" : "46R5+HM The Rocks, New South Wales",
            "global_code" : "4RRH46R5+HM"
         },
         "price_level" : 2,
         "rating" : 4,
         "reference" : "ChIJbyKrs0KuEmsRx9fE2LPB08U",
         "scope" : "GOOGLE",
         "types" : [ "bar", "restaurant", "food", "point_of_interest", "establishment" ],
         "user_ratings_total" : 145,
         "vicinity" : "106 George St, The Rocks"
      },
      {
         "geometry" : {
            "location" : {
               "lat" : -33.861702,
               "lng" : 151.209463
            },
            "viewport" : {
               "northeast" : {
                  "lat" : -33.86043797010728,
                  "lng" : 151.2107743798927
               },
               "southwest" : {
                  "lat" : -33.86313762989272,
                  "lng" : 151.2080747201072
               }
            }
         },
         "icon" : "https://maps.gstatic.com/mapfiles/place_api/icons/restaurant-71.png",
         "id" : "b7a5aac50f4ff2bd9fe4a141a25d5a6e26d8843a",
         "name" : "Neptune Palace Restaurant",
         "opening_hours" : {
            "open_now" : false
         },
         "photos" : [
            {
               "height" : 3024,
               "html_attributions" : [
                  "\u003ca href=\"https://maps.google.com/maps/contrib/109124500510284889906\"\u003eDavid Maddison\u003c/a\u003e"
               ],
               "photo_reference" : "CmRaAAAAIXZ5i-JIerz7tqlX8Hjw8LuLpv5ESB6TQSHWZJOffKn_KdvmKdkA7oM9RpzWE2jOxyWRDKwxhKAK9une09keUQj2zV2hlcdTcORlowCu6TDCUue3Xewjs-B0qpLrPN4GEhD3sjuanFg98bmInTzs2v8PGhSLL5AR674B--aUFolNIGjJ4SbnFA",
               "width" : 4032
            }
         ],
         "place_id" : "ChIJeUAY4GmuEmsRfnpI65gCjgQ",
         "plus_code" : {
            "compound_code" : "46Q5+8Q Sydney, New South Wales",
            "global_code" : "4RRH46Q5+8Q"
         },
         "price_level" : 3,
         "rating" : 4.3,
         "reference" : "ChIJeUAY4GmuEmsRfnpI65gCjgQ",
         "scope" : "GOOGLE",
         "types" : [ "restaurant", "food", "point_of_interest", "establishment" ],
         "user_ratings_total" : 379,
         "vicinity" : "Gateway Building Level 1 Corner of Pitt and, Alfred St, Sydney"
      },
      {
         "geometry" : {
            "location" : {
               "lat" : -33.8792832,
               "lng" : 151.2040568
            },
            "viewport" : {
               "northeast" : {
                  "lat" : -33.87768002010727,
                  "lng" : 151.2054665298927
               },
               "southwest" : {
                  "lat" : -33.88037967989272,
                  "lng" : 151.2027668701073
               }
            }
         },
         "icon" : "https://maps.gstatic.com/mapfiles/place_api/icons/restaurant-71.png",
         "id" : "286607dcbd4b5f8f26a505b4bce2ce5c45a4fed1",
         "name" : "Emperor's Garden Restaurant",
         "opening_hours" : {
            "open_now" : true
         },
         "photos" : [
            {
               "height" : 2736,
               "html_attributions" : [
                  "\u003ca href=\"https://maps.google.com/maps/contrib/112656089366852202518\"\u003eŠtefan Alakša\u003c/a\u003e"
               ],
               "photo_reference" : "CmRaAAAAQHHrASBRxtw4DuU9Efo99ESAg2l64kQUgtuGDOncgcu8qDU4ovLIftSKuOVnLQPJzpbdX2jWl5YeqFkanzk3webo40iFmIjLj75trRTpPUS827lCpnk5D_E_s-qOOKJDEhB-QN978iPMYBpf5SuA3H96GhRm84bmitnxbQq4oJcoJWkcaCuhsA",
               "width" : 3648
            }
         ],
         "place_id" : "ChIJwc0efCSuEmsRY3tDhX7ONts",
         "plus_code" : {
            "compound_code" : "46C3+7J Haymarket, New South Wales",
            "global_code" : "4RRH46C3+7J"
         },
         "price_level" : 2,
         "rating" : 3.5,
         "reference" : "ChIJwc0efCSuEmsRY3tDhX7ONts",
         "scope" : "GOOGLE",
         "types" : [ "restaurant", "food", "point_of_interest", "establishment" ],
         "user_ratings_total" : 702,
         "vicinity" : "96-100 Hay St, Haymarket"
      },
      {
         "geometry" : {
            "location" : {
               "lat" : -33.8687158,
               "lng" : 151.2018488
            },
            "viewport" : {
               "northeast" : {
                  "lat" : -33.86743212010728,
                  "lng" : 151.2032775798927
               },
               "southwest" : {
                  "lat" : -33.87013177989273,
                  "lng" : 151.2005779201073
               }
            }
         },
         "icon" : "https://maps.gstatic.com/mapfiles/place_api/icons/bar-71.png",
         "id" : "c599a18b1291baf3a5fb25990fc17fe2ee24e718",
         "name" : "Cargo Bar",
         "opening_hours" : {
            "open_now" : true
         },
         "photos" : [
            {
               "height" : 800,
               "html_attributions" : [
                  "\u003ca href=\"https://maps.google.com/maps/contrib/104269049167619826899\"\u003eCargo Bar\u003c/a\u003e"
               ],
               "photo_reference" : "CmRaAAAAChf6ZSNAqoI0tV4-yWuis3Lg0l4QEMfI3In_y_bPzYxYguHt22PAidBlOjjADpAcK_t0UMU_6hOAjVgTpcPqo6CUq8Uvw-Qqv34hNo5_QbOAah5CQproHI_V8F0t14gYEhAglHDTG_Yzcvyj2__rJKtyGhR01J5Wz-7Dj59E-Pei_EcDYh0vkA",
               "width" : 1200
            }
         ],
         "place_id" : "ChIJXxX3dkeuEmsRK39KITl0US8",
         "plus_code" : {
            "compound_code" : "46J2+GP Sydney, New South Wales",
            "global_code" : "4RRH46J2+GP"
         },
         "price_level" : 2,
         "rating" : 3.8,
         "reference" : "ChIJXxX3dkeuEmsRK39KITl0US8",
         "scope" : "GOOGLE",
         "types" : [
            "bar",
            "night_club",
            "restaurant",
            "food",
            "point_of_interest",
            "establishment"
         ],
         "user_ratings_total" : 1641,
         "vicinity" : "52-60 The Promenade, King Street Wharf, Darling Harbour"
      },
      {
         "geometry" : {
            "location" : {
               "lat" : -33.858406,
               "lng" : 151.184537
            },
            "viewport" : {
               "northeast" : {
                  "lat" : -33.85699782010728,
                  "lng" : 151.1858527798927
               },
               "southwest" : {
                  "lat" : -33.85969747989272,
                  "lng" : 151.1831531201073
               }
            }
         },
         "icon" : "https://maps.gstatic.com/mapfiles/place_api/icons/bar-71.png",
         "id" : "35c7aad34cdb00de544d8f83d3a1ee49e3c771bf",
         "name" : "The London Hotel",
         "opening_hours" : {
            "open_now" : true
         },
         "photos" : [
            {
               "height" : 3648,
               "html_attributions" : [
                  "\u003ca href=\"https://maps.google.com/maps/contrib/109807891112275089987\"\u003eThe London Hotel\u003c/a\u003e"
               ],
               "photo_reference" : "CmRaAAAAqH-NzqzVq6hcMDrIgwCgx5Rn7vg_T1F01lcMJjb4CTHnxojqhJygca4vLgg3G_NKL66dZlB6D2myJJz0FcP60Tvu93n5eoRptt9bwjjgFcKt3AB5H_yRTHkilTFX9rM7EhDWW2QPkXV_mKBgME8h7bG9GhQo199y6piyNPzaVtIKZ7sIBl6qsA",
               "width" : 5472
            }
         ],
         "place_id" : "ChIJWapAjLSvEmsRD_UqkZN5OEg",
         "plus_code" : {
            "compound_code" : "45RM+JR Balmain, New South Wales",
            "global_code" : "4RRH45RM+JR"
         },
         "price_level" : 2,
         "rating" : 4.3,
         "reference" : "ChIJWapAjLSvEmsRD_UqkZN5OEg",
         "scope" : "GOOGLE",
         "types" : [ "bar", "restaurant", "food", "point_of_interest", "establishment" ],
         "user_ratings_total" : 416,
         "vicinity" : "234 Darling St, Balmain"
      },
      {
         "geometry" : {
            "location" : {
               "lat" : -33.8579588,
               "lng" : 151.210081
            },
            "viewport" : {
               "northeast" : {
                  "lat" : -33.85678082010728,
                  "lng" : 151.2112821298927
               },
               "southwest" : {
                  "lat" : -33.85948047989272,
                  "lng" : 151.2085824701072
               }
            }
         },
         "icon" : "https://maps.gstatic.com/mapfiles/place_api/icons/restaurant-71.png",
         "id" : "ba14396fb2147225a8f83f67f111d6f1e86f3022",
         "name" : "Quay Restaurant",
         "opening_hours" : {
            "open_now" : false
         },
         "photos" : [
            {
               "height" : 1000,
               "html_attributions" : [
                  "\u003ca href=\"https://maps.google.com/maps/contrib/104539771185652682212\"\u003eQuay Restaurant\u003c/a\u003e"
               ],
               "photo_reference" : "CmRaAAAA56n5ZG3u_Z4Yxh7ELpK68japMKCTdzQWI_1XU8oG335d0SUAwz01-JlXLbMTPpDHym508xA5wxklhdpbV5ah3WFrlFgBNCVBdjLXdzxZxmcQBGBF9snRUPAbHT50U6DYEhB9QbXGQ7iMYpEw8YB_Mz0OGhRuzjE54-Iw1JUxYw4R8X-D9KGVBQ",
               "width" : 1500
            }
         ],
         "place_id" : "ChIJ4cQcDV2uEmsRMxTEHBIe9ZQ",
         "plus_code" : {
            "compound_code" : "46R6+R2 The Rocks, New South Wales",
            "global_code" : "4RRH46R6+R2"
         },
         "price_level" : 4,
         "rating" : 4.4,
         "reference" : "ChIJ4cQcDV2uEmsRMxTEHBIe9ZQ",
         "scope" : "GOOGLE",
         "types" : [ "restaurant", "food", "point_of_interest", "establishment" ],
         "user_ratings_total" : 679,
         "vicinity" : "Upper Overseas Passenger Terminal, The Rocks"
      },
      {
         "geometry" : {
            "location" : {
               "lat" : -33.8648016,
               "lng" : 151.2054365
            },
            "viewport" : {
               "northeast" : {
                  "lat" : -33.86345427010728,
                  "lng" : 151.2068595298927
               },
               "southwest" : {
                  "lat" : -33.86615392989273,
                  "lng" : 151.2041598701073
               }
            }
         },
         "icon" : "https://maps.gstatic.com/mapfiles/place_api/icons/lodging-71.png",
         "id" : "bc58a5ca8e9c65e7b673c6cd628d24828a104be6",
         "name" : "Travelodge Hotel Sydney Wynyard",
         "photos" : [
            {
               "height" : 2048,
               "html_attributions" : [
                  "\u003ca href=\"https://maps.google.com/maps/contrib/112804721426091817263\"\u003eTravelodge Hotel Wynyard\u003c/a\u003e"
               ],
               "photo_reference" : "CmRaAAAApXmxd7weXysBdqBPIEgaR_L6Pmfe-omm2MoNdKKACn9Twv-AN_DVqXSklAPX2-IWtwD4coTkeEl9bci5liJQ7bs2mAWE5SIVRdyodmbu7UaJ8bHfFrLMdjZRArHgxF4yEhAT4YaKWS1lvZTEDo7WHZt9GhS04benibC3StPlgw0Z7wvw4PLYzg",
               "width" : 1536
            }
         ],
         "place_id" : "ChIJDTwzJEGuEmsRw4ifQGYDkww",
         "plus_code" : {
            "compound_code" : "46P4+35 Sydney, New South Wales",
            "global_code" : "4RRH46P4+35"
         },
         "rating" : 3.8,
         "reference" : "ChIJDTwzJEGuEmsRw4ifQGYDkww",
         "scope" : "GOOGLE",
         "types" : [ "lodging", "restaurant", "food", "point_of_interest", "establishment" ],
         "user_ratings_total" : 1078,
         "vicinity" : "7-9 York St, Sydney"
      }
   ],
   "status" : "OK"
}
